edos/__init__.py
edos/api/__init__.py
edos/api/constants.py
edos/api/digitalocean/__init__.py
edos/api/digitalocean/base_api.py
edos/api/digitalocean/databases/__init__.py
edos/api/digitalocean/databases/api.py
edos/api/digitalocean/databases/helpers.py
edos/api/digitalocean/databases/models/__init__.py
edos/api/digitalocean/databases/models/cluster.py
edos/api/digitalocean/databases/models/connections.py
edos/api/digitalocean/databases/models/database.py
edos/api/digitalocean/databases/models/database_user.py
edos/api/digitalocean/databases/models/settings.py
edos/api/swarmpit/__init__.py
edos/api/swarmpit/base_api.py
edos/api/swarmpit/models/__init__.py
edos/api/swarmpit/models/memory_response.py
edos/api/swarmpit/services.py
edos/cache.py
edos/cli/__init__.py
edos/cli/common.py
edos/cli/do/__init__.py
edos/cli/do/cluster.py
edos/cli/do/database.py
edos/cli/do/spaces.py
edos/cli/docker.py
edos/cli/invoice.py
edos/commands.py
edos/config.py
edos/exceptions.py
edos/main.py
edos/services/__init__.py
edos/services/database_service.py
edos/services/docker_service.py
edos/services/invoice_service.py
edos/services/spaces_service.py
edos/services/swarmpit_service.py
edos/settings/__init__.py
edos/settings/conf.py
edos-1.13.0.dist-info/METADATA
edos-1.13.0.dist-info/WHEEL
edos-1.13.0.dist-info/entry_points.txt
edos-1.13.0.dist-info/RECORD
