Metadata-Version: 2.3
Name: edos
Version: 1.13.0
Summary: Internal tool for managing docker swarm cluster and DO services
Author: Štěpán Binko
Author-email: stepanjr@binko.cz
Requires-Python: >=3.10,<4.0
Classifier: Programming Language :: Python :: 3
Classifier: Programming Language :: Python :: 3.10
Classifier: Programming Language :: Python :: 3.11
Classifier: Programming Language :: Python :: 3.12
Classifier: Programming Language :: Python :: 3.13
Requires-Dist: PyYAML (>=6.0,<7.0)
Requires-Dist: appdirs (>=1.4.4,<2.0.0)
Requires-Dist: boto3 (>=1.34.159,<2.0.0)
Requires-Dist: click (>=8.1.7,<9.0.0)
Requires-Dist: clockify-api-client (>=0.1.0,<0.2.0)
Requires-Dist: diskcache (>=5.6.3,<6.0.0)
Requires-Dist: docker (>=7.1.0,<8.0.0)
Requires-Dist: fakturoid (>=1.5.1,<2.0.0)
Requires-Dist: httpx (>=0.27.0,<0.28.0)
Requires-Dist: paramiko (>=3.4.1,<4.0.0)
Requires-Dist: python-dateutil (>=2.8.2,<3.0.0)
Requires-Dist: tabulate (>=0.9.0,<0.10.0)
